langumo/__init__.py
langumo/__main__.py
langumo/configuration.py
langumo/building/__init__.py
langumo/building/base.py
langumo/building/mergence.py
langumo/building/miscellaneous.py
langumo/building/parsing.py
langumo/building/shuffling.py
langumo/building/splitting.py
langumo/building/tokenization.py
langumo/parsers/__init__.py
langumo/parsers/jsonstring.py
langumo/parsers/wikipedia.py
langumo/utils/__init__.py
langumo/utils/auxiliary.py
langumo/utils/colorful.py
langumo/utils/nlp.py
langumo-0.2.0.dist-info/LICENSE
langumo-0.2.0.dist-info/METADATA
langumo-0.2.0.dist-info/WHEEL
langumo-0.2.0.dist-info/entry_points.txt
langumo-0.2.0.dist-info/top_level.txt
langumo-0.2.0.dist-info/RECORD
