Metadata-Version: 2.1
Name: langumo
Version: 0.2.0
Summary: The unified corpus building environment for Language Models.
Home-page: https://github.com/affjljoo3581/langumo
Author: Jungwoo Park
Author-email: affjljoo3581@gmail.com
License: Apache-2.0
Keywords: langumo,corpus,dataset,nlp,language-model,deep-learning,machine-learning
Platform: UNKNOWN
Classifier: Environment :: Console
Classifier: Operating System :: OS Independent
Classifier: Programming Language :: Python :: 3
Classifier: Programming Language :: Python :: 3.6
Classifier: Programming Language :: Python :: 3.7
Classifier: Programming Language :: Python :: 3.8
Classifier: Topic :: Scientific/Engineering :: Artificial Intelligence
Requires-Python: >=3.6.0
Requires-Dist: nltk
Requires-Dist: colorama
Requires-Dist: pyyaml (>=5.3.1)
Requires-Dist: tqdm (>=4.46.0)
Requires-Dist: tokenizers (==0.8.1)
Requires-Dist: mwparserfromhell (>=0.5.4)
Requires-Dist: kss (==1.3.1)
